openGA/__init__.py
openGA/chromosome.py
openGA/genetic_algorithm.py
openGA/individual.py
openGA/population.py
openGA/utils.py
openGA/version.py
openGA-0.2.1.dist-info/LICENSE
openGA-0.2.1.dist-info/METADATA
openGA-0.2.1.dist-info/WHEEL
openGA-0.2.1.dist-info/top_level.txt
openGA-0.2.1.dist-info/RECORD
