Metadata-Version: 2.1
Name: openGA
Version: 0.2.1
Summary: genetic algorithm framework
Home-page: https://github.com/neal-nie/openGA
Author: Neal Nie
Author-email: neal.nie@hotmail.com
License: LGPLv3+
Keywords: genetic-algorithm optimization trade-off AI
Platform: UNKNOWN
Classifier: Development Status :: 3 - Alpha
Classifier: Intended Audience :: Developers
Classifier: Topic :: Software Development
Classifier: Topic :: Scientific/Engineering
Classifier: License :: OSI Approved :: GNU Lesser General Public License v3 or later (LGPLv3+)
Classifier: Programming Language :: Python :: 3.7
Classifier: Programming Language :: Python :: 3.8
Classifier: Programming Language :: Python :: 3.9
Requires-Dist: numpy (>=1.19.1)
Requires-Dist: pandas
